mdc/__init__.py
mdc/__main__.py
mdc/exceptions.py
mdc/mdc.py
samsung_mdc-0.1.0.dist-info/LICENSE
samsung_mdc-0.1.0.dist-info/METADATA
samsung_mdc-0.1.0.dist-info/WHEEL
samsung_mdc-0.1.0.dist-info/entry_points.txt
samsung_mdc-0.1.0.dist-info/top_level.txt
samsung_mdc-0.1.0.dist-info/RECORD
